harmonator/__init__.py
harmonator/exceptions/malformed_filename.py
harmonator/exceptions/malformed_filename.pyi
harmonator/filename_helpers.py
harmonator/filename_helpers.pyi
harmonator/harmonate.py
harmonator-0.1.2.dist-info/WHEEL
harmonator-0.1.2.dist-info/METADATA
harmonator-0.1.2.dist-info/RECORD
