Metadata-Version: 2.1
Name: harmonator
Version: 0.1.2
Summary: Harmontown Downloader
Home-page: https://github.com/Centurix/harmonator
License: UNKNOWN
Author: Chris Read
Author-email: centurix@gmail.com
Requires-Python: >=3.6,<4.0
Classifier: Development Status :: 2 - Pre-Alpha
Classifier: Intended Audience :: Developers
Classifier: Natural Language :: English
Classifier: Operating System :: POSIX :: Linux
Classifier: Programming Language :: Python
Classifier: Programming Language :: Python :: 3
Classifier: Programming Language :: Python :: 3.6
Classifier: Programming Language :: Python :: 3.7
Classifier: Topic :: Multimedia :: Video
Classifier: Topic :: Utilities
Requires-Dist: click (>=7.0,<8.0)
Project-URL: Repository, https://github.com/Centurix/harmonator
